cbmc_viewer/__init__.py
cbmc_viewer/cbmc_viewer.py
cbmc_viewer/configt.py
cbmc_viewer/coveraget.py
cbmc_viewer/ctagst.py
cbmc_viewer/filet.py
cbmc_viewer/loopt.py
cbmc_viewer/markup_code.py
cbmc_viewer/markup_link.py
cbmc_viewer/markup_summary.py
cbmc_viewer/markup_trace.py
cbmc_viewer/optionst.py
cbmc_viewer/parse.py
cbmc_viewer/propertyt.py
cbmc_viewer/reachablet.py
cbmc_viewer/report.py
cbmc_viewer/resultt.py
cbmc_viewer/runt.py
cbmc_viewer/sourcet.py
cbmc_viewer/srcloct.py
cbmc_viewer/symbol_table.py
cbmc_viewer/symbolt.py
cbmc_viewer/templates.py
cbmc_viewer/tracet.py
cbmc_viewer/util.py
cbmc_viewer/version.py
cbmc_viewer/viewer.css
cbmc_viewer/viewer.js
cbmc_viewer/viewer.py
cbmc_viewer/etc/bash_completion.d/cbmc-viewer.sh
cbmc_viewer/templates/code.jinja.html
cbmc_viewer/templates/link.jinja.html
cbmc_viewer/templates/summary.jinja.html
cbmc_viewer/templates/trace.jinja.html
cbmc_viewer-3.11.1.dist-info/licenses/LICENSE
cbmc_viewer-3.11.1.dist-info/licenses/NOTICE
cbmc_viewer-3.11.1.dist-info/METADATA
cbmc_viewer-3.11.1.dist-info/WHEEL
cbmc_viewer-3.11.1.dist-info/entry_points.txt
cbmc_viewer-3.11.1.dist-info/top_level.txt
cbmc_viewer-3.11.1.dist-info/RECORD
