Metadata-Version: 2.4
Name: cbmc-viewer
Version: 3.11.1
Summary: CBMC viewer produces a browsable summary of CBMC findings
Home-page: https://github.com/model-checking/cbmc-viewer
Author: Mark R. Tuttle
Author-email: mrtuttle@amazon.com
License: Apache License 2.0
Classifier: Programming Language :: Python :: 3
Classifier: License :: OSI Approved :: Apache Software License
Classifier: Operating System :: OS Independent
Requires-Python: >=3.7
License-File: LICENSE
License-File: NOTICE
Requires-Dist: jinja2
Requires-Dist: setuptools
Requires-Dist: voluptuous
Dynamic: license-file
